md2tex
