Metadata-Version: 1.1
Name: md2tex
Version: 0.0.9
Summary: `md2tex` is a package which convert markdown to TeX.
Home-page: https://pypi.python.org/pypi/md2tex
Author: Saito Tsutomu
Author-email: tsutomu.saito@beproud.jp
License: PSFL
Keywords: md2tex
Platform: UNKNOWN
Classifier: Development Status :: 1 - Planning
Classifier: License :: OSI Approved :: Python Software Foundation License
Classifier: Programming Language :: Python
Classifier: Topic :: Software Development
Classifier: Topic :: Scientific/Engineering
